{
  "fema_are_you_ready": {
    "file_name": "files/qumzg1s8s504",
    "file_uri": "https://generativelanguage.googleapis.com/v1beta/files/qumzg1s8s504",
    "mime_type": "application/pdf"
  },
  "household_preparedness": {
    "file_name": "files/p70ve7vad20s",
    "file_uri": "https://generativelanguage.googleapis.com/v1beta/files/p70ve7vad20s",
    "mime_type": "application/pdf"
  },
  "flood_preparedness": {
    "file_name": "files/hi1ljj2l6tbf",
    "file_uri": "https://generativelanguage.googleapis.com/v1beta/files/hi1ljj2l6tbf",
    "mime_type": "application/pdf"
  },
  "wildfire_preparedness": {
    "file_name": "files/1kwa01m9fonu",
    "file_uri": "https://generativelanguage.googleapis.com/v1beta/files/1kwa01m9fonu",
    "mime_type": "application/pdf"
  },
  "wildfire_toolkit": {
    "file_name": "files/b1k1pqnwwca6",
    "file_uri": "https://generativelanguage.googleapis.com/v1beta/files/b1k1pqnwwca6",
    "mime_type": "application/pdf"
  },
  "earthquake_tsunami_guide": {
    "file_name": "files/ofw0u5h8f10i",
    "file_uri": "https://generativelanguage.googleapis.com/v1beta/files/ofw0u5h8f10i",
    "mime_type": "application/pdf"
  },
  "winter_storm_guide": {
    "file_name": "files/c5shal90cqt8",
    "file_uri": "https://generativelanguage.googleapis.com/v1beta/files/c5shal90cqt8",
    "mime_type": "application/pdf"
  },
  "canada_power_outage": {
    "file_name": "files/p8d9btrt0u2j",
    "file_uri": "https://generativelanguage.googleapis.com/v1beta/files/p8d9btrt0u2j",
    "mime_type": "application/pdf"
  },
  "bc_power_outage": {
    "file_name": "files/vtg91tflfepw",
    "file_uri": "https://generativelanguage.googleapis.com/v1beta/files/vtg91tflfepw",
    "mime_type": "application/pdf"
  },
  "ont_power_outage": {
    "file_name": "files/061bz5qxo0qr",
    "file_uri": "https://generativelanguage.googleapis.com/v1beta/files/061bz5qxo0qr",
    "mime_type": "application/pdf"
  }
}